LICENSE
README.rst
microarch.py
setup.py
microarch.egg-info/PKG-INFO
microarch.egg-info/SOURCES.txt
microarch.egg-info/dependency_links.txt
microarch.egg-info/requires.txt
microarch.egg-info/top_level.txt